AUTHORS
CHANGES.rst
LICENSE
MANIFEST.in
README.rst
setup.cfg
setup.py
pyneqsys/__init__.py
pyneqsys/_release.py
pyneqsys/_sympy.py
pyneqsys/core.py
pyneqsys/plotting.py
pyneqsys/solvers.py
pyneqsys/symbolic.py
pyneqsys.egg-info/PKG-INFO
pyneqsys.egg-info/SOURCES.txt
pyneqsys.egg-info/dependency_links.txt
pyneqsys.egg-info/requires.txt
pyneqsys.egg-info/top_level.txt
pyneqsys/tests/__init__.py
pyneqsys/tests/test_backends.py
pyneqsys/tests/test_core.py
pyneqsys/tests/test_ipopt.py
pyneqsys/tests/test_levmar.py
pyneqsys/tests/test_symbolic.py