Metadata-Version: 2.1
Name: pyneqsys
Version: 0.5.6
Summary: Package for numerically solving symbolically defined systems of non-linear equations.
Home-page: https://github.com/bjodah/pyneqsys
Author: Bjoern I. Dahlgren 
Author-email: bjodah@gmail.com
License: BSD
Platform: UNKNOWN
Classifier: Development Status :: 4 - Beta
Classifier: License :: OSI Approved :: BSD License
Classifier: Operating System :: OS Independent
Classifier: Topic :: Scientific/Engineering
Classifier: Topic :: Scientific/Engineering :: Mathematics
Provides-Extra: docs
Provides-Extra: all
Provides-Extra: testing
Provides-Extra: symbolic
Provides-Extra: solvers
